{
    "fetched_at": 1772796064,
    "ttl": 60,
    "data": {
        "id": 3,
        "name": "Ilam-1",
        "name_np": "क्षेत्र नं. १",
        "province": "Koshi",
        "district": "Ilam",
        "total_votes_counted": 0,
        "total_registered_voters": 112320,
        "total_cast_votes": 0,
        "counting_complete": false,
        "status": "pending",
        "candidates": [
            {
                "id": 340081,
                "name": "Nishkal Rai",
                "name_np": "निश्कल राई",
                "party": "Nepali Congress",
                "party_abbr": "NC",
                "party_color": "#1e3a8a",
                "party_name": "नेपाली काँग्रेस",
                "image_url": "https:\/\/file-r2.hamropatro.com\/election-images\/2082\/candidates\/340081.jpg",
                "votes": 0,
                "percentage": 0,
                "position": 1,
                "status": "trailing"
            },
            {
                "id": 339884,
                "name": "Kazi Man Kagate",
                "name_np": "काजी मान कागते",
                "party": "CPN-UML",
                "party_abbr": "UML",
                "party_color": "#dc2626",
                "party_name": "नेपाल कम्युनिष्ट पार्टी (एकीकृत मार्क्सवादी लेनिनवादी)",
                "image_url": "https:\/\/file-r2.hamropatro.com\/election-images\/2082\/candidates\/339884.jpg",
                "votes": 0,
                "percentage": 0,
                "position": 2,
                "status": "trailing"
            },
            {
                "id": 340213,
                "name": "Bimal Gadal",
                "name_np": "विमल गदाल",
                "party": "Rastriya Swatantra Party",
                "party_abbr": "RSP",
                "party_color": "#7c3aed",
                "party_name": "राष्ट्रिय स्वतन्त्र पार्टी",
                "image_url": "https:\/\/file-r2.hamropatro.com\/election-images\/2082\/candidates\/340213.jpg",
                "votes": 0,
                "percentage": 0,
                "position": 3,
                "status": "trailing"
            }
        ],
        "winner": null
    }
}